cookie_manager/__init__.py
cookie_manager/cookie_manager.py
cookie_manager/security_decorator.py
tests/__init__.py
tests/conftest.py
tests/test_cookie_manager.py
cookie_manager-1.2.3.dist-info/LICENSE
cookie_manager-1.2.3.dist-info/METADATA
cookie_manager-1.2.3.dist-info/WHEEL
cookie_manager-1.2.3.dist-info/top_level.txt
cookie_manager-1.2.3.dist-info/RECORD
