Metadata-Version: 2.1
Name: cookie-manager
Version: 1.2.3
Summary: Signed cookie manager for communication between multiple trusted services.
Home-page: https://github.com/ScholarPack/cookie-manager
Author: ScholarPack
Author-email: dev@scholarpack.com
License: UNKNOWN
Platform: UNKNOWN
Classifier: Development Status :: 5 - Production/Stable 
Classifier: Programming Language :: Python :: 3
Classifier: License :: OSI Approved :: GNU Lesser General Public License v3 (LGPLv3)
Classifier: Operating System :: OS Independent
Requires-Python: >=3.6
Requires-Dist: itsdangerous (>=1.1.0)
